choicetypes/__init__.py
choicetypes/choice.py
choicetypes-0.1.0rc1.dist-info/LICENSE
choicetypes-0.1.0rc1.dist-info/WHEEL
choicetypes-0.1.0rc1.dist-info/METADATA
choicetypes-0.1.0rc1.dist-info/RECORD
