Metadata-Version: 2.1
Name: choicetypes
Version: 0.1.0rc1
Summary: Powerful and simple algebraic sum types in Python.
Home-page: https://github.com/samwaterbury/choicetypes
License: MIT
Author: Sam Waterbury
Author-email: samwaterbury1@gmail.com
Requires-Python: >=3.7,<4.0
Classifier: Intended Audience :: Developers
Classifier: License :: OSI Approved :: MIT License
Classifier: Programming Language :: Python
Classifier: Programming Language :: Python :: 3
Classifier: Programming Language :: Python :: 3.7
Classifier: Programming Language :: Python :: 3.8
Classifier: Programming Language :: Python :: 3.9
Classifier: Programming Language :: Python :: 3.10
Project-URL: Repository, https://github.com/samwaterbury/choicetypes
